saler_reporter/__init__.py
saler_reporter/reporter.py
yet_another_shreporter-0.1.0.dist-info/METADATA
yet_another_shreporter-0.1.0.dist-info/WHEEL
yet_another_shreporter-0.1.0.dist-info/entry_points.txt
yet_another_shreporter-0.1.0.dist-info/top_level.txt
yet_another_shreporter-0.1.0.dist-info/RECORD
